nwb_linkml/__init__.py
nwb_linkml/adapters/__init__.py
nwb_linkml/adapters/adapter.py
nwb_linkml/adapters/classes.py
nwb_linkml/adapters/namespaces.py
nwb_linkml/adapters/schema.py
nwb_linkml/io.py
nwb_linkml/lang_elements.py
nwb_linkml/map.py
nwb_linkml/maps/__init__.py
nwb_linkml/maps/dtype.py
nwb_linkml/maps/preload.py
nwb_linkml/maps/quantity.py
nwb_linkml/models/core.nwb.base.py
nwb_linkml/models/core.nwb.behavior.py
nwb_linkml/models/core.nwb.device.py
nwb_linkml/models/core.nwb.ecephys.py
nwb_linkml/models/core.nwb.epoch.py
nwb_linkml/models/core.nwb.file.py
nwb_linkml/models/core.nwb.icephys.py
nwb_linkml/models/core.nwb.image.py
nwb_linkml/models/core.nwb.misc.py
nwb_linkml/models/core.nwb.ogen.py
nwb_linkml/models/core.nwb.ophys.py
nwb_linkml/models/core.nwb.retinotopy.py
nwb_linkml/models/core.py
nwb_linkml/models/hdmf-common.base.py
nwb_linkml/models/hdmf-common.py
nwb_linkml/models/hdmf-common.sparse.py
nwb_linkml/models/hdmf-common.table.py
nwb_linkml/models/hdmf-experimental.experimental.py
nwb_linkml/models/hdmf-experimental.py
nwb_linkml/models/hdmf-experimental.resources.py
nwb_linkml/models/nwb.language.py
nwb_linkml/namespaces.py
nwb_linkml/plot.py
nwb_linkml/schema/core.nwb.base.yaml
nwb_linkml/schema/core.nwb.behavior.yaml
nwb_linkml/schema/core.nwb.device.yaml
nwb_linkml/schema/core.nwb.ecephys.yaml
nwb_linkml/schema/core.nwb.epoch.yaml
nwb_linkml/schema/core.nwb.file.yaml
nwb_linkml/schema/core.nwb.icephys.yaml
nwb_linkml/schema/core.nwb.image.yaml
nwb_linkml/schema/core.nwb.misc.yaml
nwb_linkml/schema/core.nwb.ogen.yaml
nwb_linkml/schema/core.nwb.ophys.yaml
nwb_linkml/schema/core.nwb.retinotopy.yaml
nwb_linkml/schema/core.yaml
nwb_linkml/schema/hdmf-common.base.yaml
nwb_linkml/schema/hdmf-common.sparse.yaml
nwb_linkml/schema/hdmf-common.table.yaml
nwb_linkml/schema/hdmf-common.yaml
nwb_linkml/schema/hdmf-experimental.experimental.yaml
nwb_linkml/schema/hdmf-experimental.resources.yaml
nwb_linkml/schema/hdmf-experimental.yaml
nwb_linkml-0.1.0.dist-info/LICENSE
nwb_linkml-0.1.0.dist-info/METADATA
nwb_linkml-0.1.0.dist-info/WHEEL
nwb_linkml-0.1.0.dist-info/RECORD
